{"file": "dental/files/עדכון_על_רכישת_הפעילות_הביטוחית_של_חברת_שירביט_על_ידי_הראל.pdf", "domain": "dental", "kind": "pdf", "url": "https://www.harel-group.co.il/Insurance/car/policies/DocLib/עדכון%20על%20רכישת%20הפעילות%20הביטוחית%20של%20חברת%20שירביט%20על%20ידי%20הראל.pdf", "pages": [{"page": 1, "text": "2021 דצמבר 26: תאריך\n\nעדכון על רכישת הפעילות הביטוחית של חברת שירביט ע\"י הראל\n\nשלום רב,\n\n, בהמשך להודעות קודמות, אנו מבקשים לעדכן כי על פי הסכם בין שירביט חברה לביטוח בע\"מ (\" הראל \" : )להלן 520004078 . \"( והראל חברה לביטוח בע\"מ, ח.פ שירביט \" : )להלן 512904608 . ח.פ .2021 דצמבר 1 הועברה כל הפעילות הביטוחית )זכויות והתחייבויות( של שירביט להראל ביום חשוב לנו להדגיש, שזכויות המבוטחים של שירביט לא ניפגעו כתוצאה מהמעבר ופוליסות הביטוח הקיימות בשירביט נכון למועד עדכון זה, כפי שהן ועל פי תנאיהן הקיימים, הועברו להראל באותם\n\n. תנאים, ללא שינוי\n\nשמות הפוליסות המועברות:\n\n| )הפוליסה( המוצר שם                                                                           |\n|----------------------------------------------------------------------------------------------|\n| טון 3.5 עד ומסחרי פרטי רכב לביטוח פוליסה לרכב שיר                                            |\n| חובה רכב פוליסת                                                                              |\n| 3.5 מעל מסחרי שאינו רכב וכלי פרטי שאינו רכב כלי לבטוח פוליסה טון                             |\n| לדירה מקיף בטוח                                                                              |\n| לנוסע שיר                                                                                    |\n| קבלניות עבודות ביטוח                                                                         |\n| 2018\" \"שירביט - ביט מהדורת קבלניות עבודות                                                    |\n| הנדסי מכני ציוד לביטוח פוליסה                                                                |\n| ביט בנוסח הנדסי מכני ציוד ביטוח                                                              |\n| מקצועית אחריות בטוח                                                                          |\n| המוצר חבות בטוח                                                                              |\n| ביט בנוסח המוצר אחריות לביטוח פוליסה                                                         |\n| בטחון מיוחדים, וטיפולים השתלות לילד, בטחון כולל: בריאות מור משפחתית והגנה בריאות סל לבריאות, |\n| לעסק שיר                                                                                     |\n| ביט בנוסח שלישי צד כלפי אחריות                                                               |\n| YACHT/BOAT COVER - ימי                                                                       |"}, {"page": 2, "text": "| BEST PA לפרט אישיות תאונות                                          |\n|---------------------------------------------------------------------|\n| מסחרי או פרטי רכב לשוכרי עצמית השתתפות דמי )ביטוח C.D.W טון( 3.5 עד |\n| CDW-VIP                                                             |\n| לסחר חובה רכב ביטוח                                                 |\n| משפטית הגנה הוצאת לביטוח פוליסה                                     |\n| SHIR MEDIC                                                          |\n\nומידע אודות שירביט https://www.harel-group.co.il מידע אודות קבוצת הראל אפשר למצוא באתר . https://www.shirbit.co.il מבית הראל חברה לביטוח בע\"מ אפשר למצוא באתר או\n\n09-8356712 , מספר פקס 076-8622260 לכל שאלה או הבהרה אפשר לפנות אלינו במספר הטלפון . Sherut@shirbit.co.il לכתובת המייל\n\n, בברכה\n\nהראל חברה לביטוח בע\"מ"}]}