{"file": "health/pages/organ-transplant-overseas.txt", "domain": "health", "kind": "txt", "url": "https://www.harel-group.co.il/insurance/health/information/organ-transplant-overseas", "pages": [{"page": 1, "text": "המסע להשתלות איברים בחו&quot;ל | הראל ביטוח ופיננסים דלג לתוכן ראשי דלג לתפריט תחתון פעולות נפוצות ביטוח חיסכון ופנסיה הראל פיננסים משכנתא והלוואה חיפוש אזור אישי ביטוח ביטוח בריאות כדאי לדעת המסע להשתלות איברים בחו&quot;ל המסע להשתלות איברים בחו&quot;ל השתלת איבר בחו&quot;ל היא אירוע שיכול לסחוף משפחה שלמה למערבולת כלכלית, רגשית ולוגיסטית. קראו כיצד ביטוח בריאות פרטי יכול לסייע למטופלים ולמשפחותיהם להתמודד עם המורכבות הזו ולדאוג לבריאות המושתלים. ביטוח בריאות פרטי שנמצא לצדך ברגעים הקשים ביותר ביטוח בריאות בהראל לשקט הנפשי שלך פתרונות שמתאימים לצרכים המשתנים של כל המשפחה לפרטים והצטרפות ההמתנה משתלמת? מעבר לים – השתלות איברים בחו&quot;ל אולי יעניין אתכם: דוהרים קדימה עם רכיבה טיפולית לילדים כשהמילים לא מספיקות - קלינאות תקשורת לילדים ביטוח אובדן כושר עבודה - הביטוח ששומר על הפרנסה שלך חשיבות ביטוח הבריאות הפרטי למקרה קטסטרופה כתבות נוספות שיכולות לעניין אתכם שם בשבילך – ביטוח מחלות קשות ​​​​גילוי מחלה קשה יכול להתפרץ כרעם ביום בהיר בחייהם של צעירים ומבוגרים כאחד. רכישת ביטוח מחלות קשות כשאנחנו בריאים יכול לספק לנו את היציבות הכלכלית שאנו זקוקים לה בתקופה המאתגרת של המחלה וההחלמה. ביטוחי בריאות אחרי הרפורמה ב-1.10.23 נכנסה לתוקף חלק מהרפורמה בביטוחי הבריאות, הקובעת מבנה חדש לכיסויים השונים של ביטוחי הבריאות הפרטיים. מה משמעות הרפורמה עבורכם המבוטחים? פרטים בכתבה הבאה. פורטלים מקצועיים אודות קבוצת הראל כניסה לסוכנים כניסה למעסיקים כניסה לספקים כניסה לרופאים קריירה בהראל הראל לשירותך שירות לקוחות הצהרת נגישות אחריות תאגידית עיון במידע אישי תנאי שימוש ומדיניות הפרטיות Investor Relations אמנת השירות מידע בדבר תגמול לבעל רישיון תובענות ייצוגיות - הודעות לציבור עדכון בגיר לצורך זיהוי באתר &quot;הר הביטוח&quot; שירות ללקוחות כבדי שמיעה - Sign Now בססח - ביטוח אשראי שירות ותמיכה לחברות Fintech אימות נתוני פרוייקטים בבנייה מועדון זמן הראל עדכונים בעקבות המצב הבטחוני ביטוח ביטוח רכב ביטוח חיים ביטוח נסיעות לחו&quot;ל ביטוח אובדן כושר עבודה ביטוח בריאות ביטוח מחלות קשות ביטוח תאונות אישיות ביטוח סיעודי ביטוח עובדים זרים ותיירים ביטוח שיניים ביטוח מקיף לרכב ביטוח חובה לרכב ביטוח צד ג&#x27; לרכב ביטוח משכנתא ביטוח עסק ביטוח דירה ארכיון פוליסות שירביט - מוצרי ביטוח שירביט - ארכיון פוליסות פנסיה, גמל, השתלמות וחיסכון הראל Fidelity קרנות פנסיה קרנות השתלמות הלוואה מחיסכון ארוך טווח קופות גמל ביטוח מנהלים (ביטוח חיים פנסיוני) קופות מרכזיות למעסיק משכנתא + קופת גמל חיסכון לכל ילד משכנתא 60+ (משכנתא הפוכה) קופת גמל להשקעה חיסכון והשקעה המרכז לתכנון כלכלי מתקדם פיננסים והשקעות ניהול תיקי השקעות השקעות אלטרנטיביות מחקר וסקירות קרנות נאמנות קריירה בהראל פורטלים מקצועיים אודות קבוצת הראל כניסה לסוכנים כניסה למעסיקים כניסה לספקים כניסה לרופאים הראל לשירותך שירות לקוחות הצהרת נגישות אחריות תאגידית עיון במידע אישי תנאי שימוש ומדיניות הפרטיות Investor Relations אמנת השירות מידע בדבר תגמול לבעל רישיון תובענות ייצוגיות - הודעות לציבור עדכון בגיר לצורך זיהוי באתר &quot;הר הביטוח&quot; שירות ללקוחות כבדי שמיעה - Sign Now בססח - ביטוח אשראי שירות ותמיכה לחברות Fintech אימות נתוני פרוייקטים בבנייה מועדון זמן הראל עדכונים בעקבות המצב הבטחוני ביטוח ביטוח רכב ביטוח חיים ביטוח נסיעות לחו&quot;ל ביטוח אובדן כושר עבודה ביטוח בריאות ביטוח מחלות קשות ביטוח תאונות אישיות ביטוח סיעודי ביטוח עובדים זרים ותיירים ביטוח שיניים ביטוח מקיף לרכב ביטוח חובה לרכב ביטוח צד ג&#x27; לרכב ביטוח משכנתא ביטוח עסק ביטוח דירה ארכיון פוליסות שירביט - מוצרי ביטוח שירביט - ארכיון פוליסות פנסיה, גמל, השתלמות וחיסכון הראל Fidelity קרנות פנסיה קרנות השתלמות הלוואה מחיסכון ארוך טווח קופות גמל ביטוח מנהלים (ביטוח חיים פנסיוני) קופות מרכזיות למעסיק משכנתא + קופת גמל חיסכון לכל ילד משכנתא 60+ (משכנתא הפוכה) קופת גמל להשקעה חיסכון והשקעה המרכז לתכנון כלכלי מתקדם פיננסים והשקעות ניהול תיקי השקעות השקעות אלטרנטיביות מחקר וסקירות קרנות נאמנות"}]}